pyfish/__init__.py
pyfish/core.py
pyfish/main.py
pyfish-1.0.0.dist-info/LICENSE
pyfish-1.0.0.dist-info/METADATA
pyfish-1.0.0.dist-info/WHEEL
pyfish-1.0.0.dist-info/entry_points.txt
pyfish-1.0.0.dist-info/top_level.txt
pyfish-1.0.0.dist-info/RECORD
