Metadata-Version: 2.1
Name: pyfish
Version: 1.0.0
Summary: Plotting tool for evolutionary population dynamics. Creates a Fish (Muller) plot.
Home-page: https://bitbucket.org/schwarzlab/pyfish
Author: Adam Streck, Tom L. Kaufmann
Author-email: adam.streck@mdc-berlin.de
License: MIT
Keywords: plot genomics visualization
Platform: UNKNOWN
Requires-Python: >=3.8
License-File: LICENSE
Requires-Dist: numpy (>=1.14)
Requires-Dist: pandas (>=1.0)
Requires-Dist: scipy (>=1.0)
Requires-Dist: matplotlib (>=3.0)
Requires-Dist: pytest (>=3.0)
